sefrone_bootstrap/__init__.py
sefrone_bootstrap/bootstrap_package.py
sefrone_bootstrap-1.1.0.dist-info/METADATA
sefrone_bootstrap-1.1.0.dist-info/WHEEL
sefrone_bootstrap-1.1.0.dist-info/top_level.txt
sefrone_bootstrap-1.1.0.dist-info/RECORD
