Metadata-Version: 2.1
Name: sefrone-bootstrap
Version: 1.1.0
Summary: A Python package to provide build helpers for sefrone backend projects
Home-page: https://bitbucket.org/sefrone/sefrone_pypi
Author: Sefrone
Author-email: contact@sefrone.com
License: UNKNOWN
Platform: UNKNOWN
Classifier: Programming Language :: Python :: 3
Classifier: License :: Other/Proprietary License
Classifier: Operating System :: OS Independent
Requires-Python: >=3.7
